.gitignore
LICENSE
README.md
README.txt
setup.cfg.sample
setup.py
test/test.html
test/test.py
welder/__init__.py
welder.egg-info/PKG-INFO
welder.egg-info/SOURCES.txt
welder.egg-info/dependency_links.txt
welder.egg-info/not-zip-safe
welder.egg-info/requires.txt
welder.egg-info/top_level.txt